{
  "id": "n4-lesson-39",
  "title": "美容院",
  "titleFurigana": "びよういん",
  "level": "N4",
  "source": "JpStudy Original",
  "publishedAt": "2026-02-01",
  "translation": "Tiệm cắt tóc (Làm đẹp)",
  "paragraphs": [
    [
      {
        "surface": "今日",
        "reading": "きょう",
        "meaningVi": "hôm nay",
        "meaningEn": "today"
      },
      {
        "surface": "は",
        "reading": "",
        "meaningVi": "",
        "meaningEn": ""
      },
      {
        "surface": "美容院",
        "reading": "びよういん",
        "meaningVi": "tiệm làm tóc",
        "meaningEn": "beauty salon"
      },
      {
        "surface": "へ",
        "reading": "",
        "meaningVi": "đến",
        "meaningEn": "to"
      },
      {
        "surface": "行",
        "reading": "い",
        "meaningVi": "đi",
        "meaningEn": "go"
      },
      {
        "surface": "って",
        "reading": "",
        "meaningVi": "",
        "meaningEn": ""
      },
      {
        "surface": "、",
        "reading": "",
        "meaningVi": "",
        "meaningEn": ""
      },
      {
        "surface": "髪",
        "reading": "かみ",
        "meaningVi": "tóc",
        "meaningEn": "hair"
      },
      {
        "surface": "を",
        "reading": "",
        "meaningVi": "",
        "meaningEn": ""
      },
      {
        "surface": "切",
        "reading": "き",
        "meaningVi": "cắt",
        "meaningEn": "cut"
      },
      {
        "surface": "ってもらいました",
        "reading": "",
        "meaningVi": "được/nhờ (cắt)",
        "meaningEn": "had it cut"
      },
      {
        "surface": "。",
        "reading": "",
        "meaningVi": "",
        "meaningEn": ""
      }
    ],
    [
      {
        "surface": "店員",
        "reading": "てんいん",
        "meaningVi": "nhân viên",
        "meaningEn": "staff"
      },
      {
        "surface": "：",
        "reading": "",
        "meaningVi": "",
        "meaningEn": ""
      },
      {
        "surface": "今日",
        "reading": "きょう",
        "meaningVi": "hôm nay",
        "meaningEn": "today"
      },
      {
        "surface": "は",
        "reading": "",
        "meaningVi": "",
        "meaningEn": ""
      },
      {
        "surface": "どう",
        "reading": "",
        "meaningVi": "thế nào",
        "meaningEn": "how"
      },
      {
        "surface": "します",
        "reading": "",
        "meaningVi": "làm",
        "meaningEn": "do"
      },
      {
        "surface": "か",
        "reading": "",
        "meaningVi": "",
        "meaningEn": ""
      },
      {
        "surface": "。",
        "reading": "",
        "meaningVi": "",
        "meaningEn": ""
      }
    ],
    [
      {
        "surface": "私",
        "reading": "わたし",
        "meaningVi": "tôi",
        "meaningEn": "I"
      },
      {
        "surface": "：",
        "reading": "",
        "meaningVi": "",
        "meaningEn": ""
      },
      {
        "surface": "短",
        "reading": "みじか",
        "meaningVi": "ngắn",
        "meaningEn": "short"
      },
      {
        "surface": "く",
        "reading": "",
        "meaningVi": "",
        "meaningEn": ""
      },
      {
        "surface": "して",
        "reading": "",
        "meaningVi": "làm (cho ngắn)",
        "meaningEn": "make it"
      },
      {
        "surface": "ください",
        "reading": "",
        "meaningVi": "hãy",
        "meaningEn": "please"
      },
      {
        "surface": "。",
        "reading": "",
        "meaningVi": "",
        "meaningEn": ""
      }
    ],
    [
      {
        "surface": "それに",
        "reading": "",
        "meaningVi": "ngoài ra/hơn nữa",
        "meaningEn": "besides"
      },
      {
        "surface": "、",
        "reading": "",
        "meaningVi": "",
        "meaningEn": ""
      },
      {
        "surface": "少",
        "reading": "すこ",
        "meaningVi": "một chút",
        "meaningEn": "little"
      },
      {
        "surface": "し",
        "reading": "",
        "meaningVi": "",
        "meaningEn": ""
      },
      {
        "surface": "染",
        "reading": "そ",
        "meaningVi": "nhuộm",
        "meaningEn": "dye"
      },
      {
        "surface": "めたい",
        "reading": "",
        "meaningVi": "muốn",
        "meaningEn": "want to"
      },
      {
        "surface": "んですが",
        "reading": "",
        "meaningVi": "giải thích ý muốn",
        "meaningEn": "explanatory"
      },
      {
        "surface": "。",
        "reading": "",
        "meaningVi": "",
        "meaningEn": ""
      }
    ],
    [
      {
        "surface": "髪型",
        "reading": "かみがた",
        "meaningVi": "kiểu tóc",
        "meaningEn": "hairstyle"
      },
      {
        "surface": "を",
        "reading": "",
        "meaningVi": "",
        "meaningEn": ""
      },
      {
        "surface": "変",
        "reading": "か",
        "meaningVi": "thay đổi",
        "meaningEn": "change"
      },
      {
        "surface": "える",
        "reading": "",
        "meaningVi": "",
        "meaningEn": ""
      },
      {
        "surface": "と",
        "reading": "",
        "meaningVi": "hễ/khi",
        "meaningEn": "when"
      },
      {
        "surface": "、",
        "reading": "",
        "meaningVi": "",
        "meaningEn": ""
      },
      {
        "surface": "気分",
        "reading": "きぶん",
        "meaningVi": "tâm trạng",
        "meaningEn": "mood"
      },
      {
        "surface": "も",
        "reading": "",
        "meaningVi": "cũng",
        "meaningEn": "also"
      },
      {
        "surface": "変",
        "reading": "か",
        "meaningVi": "thay đổi",
        "meaningEn": "change"
      },
      {
        "surface": "わります",
        "reading": "",
        "meaningVi": "",
        "meaningEn": ""
      },
      {
        "surface": "ね",
        "reading": "",
        "meaningVi": "nhỉ",
        "meaningEn": "isn't it"
      },
      {
        "surface": "。",
        "reading": "",
        "meaningVi": "",
        "meaningEn": ""
      }
    ]
  ]
}