[
    {
        "term": "います",
        "reading": "います",
        "kanjiMeaning": null,
        "meaning_vi": "có (người / động vật)",
        "meaning_en": "exist / be (animate)",
        "level": "N5",
        "tags": "minna_10,verb"
    },
    {
        "term": "あります",
        "reading": "あります",
        "kanjiMeaning": "hữu",
        "meaning_vi": "có (đồ vật)",
        "meaning_en": "exist / be (inanimate)",
        "level": "N5",
        "tags": "minna_10,verb"
    },
    {
        "term": "いろいろ",
        "reading": "いろいろ",
        "kanjiMeaning": null,
        "meaning_vi": "nhiều thứ khác nhau",
        "meaning_en": "various",
        "level": "N5",
        "tags": "minna_10,adj_na"
    },
    {
        "term": "男の人",
        "reading": "おとこのひと",
        "kanjiMeaning": "nam nhân",
        "meaning_vi": "người đàn ông",
        "meaning_en": "man",
        "level": "N5",
        "tags": "minna_10,noun"
    },
    {
        "term": "女の人",
        "reading": "おんなのひと",
        "kanjiMeaning": "nữ nhân",
        "meaning_vi": "người đàn bà",
        "meaning_en": "woman",
        "level": "N5",
        "tags": "minna_10,noun"
    },
    {
        "term": "男の子",
        "reading": "おとこのこ",
        "kanjiMeaning": "nam tử",
        "meaning_vi": "bé trai / con trai",
        "meaning_en": "boy",
        "level": "N5",
        "tags": "minna_10,noun"
    },
    {
        "term": "女の子",
        "reading": "おんなのこ",
        "kanjiMeaning": "nữ tử",
        "meaning_vi": "bé gái / con gái",
        "meaning_en": "girl",
        "level": "N5",
        "tags": "minna_10,noun"
    },
    {
        "term": "犬",
        "reading": "いぬ",
        "kanjiMeaning": "khuyển",
        "meaning_vi": "con chó",
        "meaning_en": "dog",
        "level": "N5",
        "tags": "minna_10,animal"
    },
    {
        "term": "猫",
        "reading": "ねこ",
        "kanjiMeaning": "miêu",
        "meaning_vi": "con mèo",
        "meaning_en": "cat",
        "level": "N5",
        "tags": "minna_10,animal"
    },
    {
        "term": "パンダ",
        "reading": "ぱんだ",
        "kanjiMeaning": null,
        "meaning_vi": "gấu trúc",
        "meaning_en": "panda",
        "level": "N5",
        "tags": "minna_10,animal"
    },
    {
        "term": "象",
        "reading": "ぞう",
        "kanjiMeaning": "tượng",
        "meaning_vi": "con voi",
        "meaning_en": "elephant",
        "level": "N5",
        "tags": "minna_10,animal"
    },
    {
        "term": "木",
        "reading": "き",
        "kanjiMeaning": "mộc",
        "meaning_vi": "cây",
        "meaning_en": "tree / wood",
        "level": "N5",
        "tags": "minna_10,noun"
    },
    {
        "term": "物",
        "reading": "もの",
        "kanjiMeaning": "vật",
        "meaning_vi": "vật / đồ vật",
        "meaning_en": "thing",
        "level": "N5",
        "tags": "minna_10,noun"
    },
    {
        "term": "電池",
        "reading": "でんち",
        "kanjiMeaning": "điện trì",
        "meaning_vi": "pin",
        "meaning_en": "battery",
        "level": "N5",
        "tags": "minna_10,things"
    },
    {
        "term": "箱",
        "reading": "はこ",
        "kanjiMeaning": "tương",
        "meaning_vi": "hộp",
        "meaning_en": "box",
        "level": "N5",
        "tags": "minna_10,things"
    },
    {
        "term": "スイッチ",
        "reading": "すいっち",
        "kanjiMeaning": null,
        "meaning_vi": "công tắc",
        "meaning_en": "switch",
        "level": "N5",
        "tags": "minna_10,things"
    },
    {
        "term": "冷蔵庫",
        "reading": "れいぞうこ",
        "kanjiMeaning": "lãnh tàng khố",
        "meaning_vi": "tủ lạnh",
        "meaning_en": "refrigerator",
        "level": "N5",
        "tags": "minna_10,electronics"
    },
    {
        "term": "テーブル",
        "reading": "てーぶる",
        "kanjiMeaning": null,
        "meaning_vi": "bàn (ăn)",
        "meaning_en": "table",
        "level": "N5",
        "tags": "minna_10,furniture"
    },
    {
        "term": "ベッド",
        "reading": "べっど",
        "kanjiMeaning": null,
        "meaning_vi": "giường",
        "meaning_en": "bed",
        "level": "N5",
        "tags": "minna_10,furniture"
    },
    {
        "term": "棚",
        "reading": "たな",
        "kanjiMeaning": "bằng",
        "meaning_vi": "giá sách / kệ",
        "meaning_en": "shelf",
        "level": "N5",
        "tags": "minna_10,furniture"
    },
    {
        "term": "ドア",
        "reading": "どあ",
        "kanjiMeaning": null,
        "meaning_vi": "cửa (ra vào)",
        "meaning_en": "door",
        "level": "N5",
        "tags": "minna_10,place"
    },
    {
        "term": "窓",
        "reading": "まど",
        "kanjiMeaning": "song",
        "meaning_vi": "cửa sổ",
        "meaning_en": "window",
        "level": "N5",
        "tags": "minna_10,place"
    },
    {
        "term": "ポスト",
        "reading": "ぽすと",
        "kanjiMeaning": null,
        "meaning_vi": "hộp thư",
        "meaning_en": "mailbox / postbox",
        "level": "N5",
        "tags": "minna_10,place"
    },
    {
        "term": "ビル",
        "reading": "びる",
        "kanjiMeaning": null,
        "meaning_vi": "tòa nhà",
        "meaning_en": "building",
        "level": "N5",
        "tags": "minna_10,place"
    },
    {
        "term": "公園",
        "reading": "こうえん",
        "kanjiMeaning": "công viên",
        "meaning_vi": "công viên",
        "meaning_en": "park",
        "level": "N5",
        "tags": "minna_10,place"
    },
    {
        "term": "喫茶店",
        "reading": "きっさてん",
        "kanjiMeaning": "khiết trà điếm",
        "meaning_vi": "quán giải khát / quán cà phê",
        "meaning_en": "coffee shop",
        "level": "N5",
        "tags": "minna_10,place"
    },
    {
        "term": "本屋",
        "reading": "ほんや",
        "kanjiMeaning": "bản ốc",
        "meaning_vi": "hiệu sách",
        "meaning_en": "bookstore",
        "level": "N5",
        "tags": "minna_10,place"
    },
    {
        "term": "屋",
        "reading": "や",
        "kanjiMeaning": "ốc",
        "meaning_vi": "cửa hàng ~",
        "meaning_en": "~ store",
        "level": "N5",
        "tags": "minna_10,suffix"
    },
    {
        "term": "乗り場",
        "reading": "のりば",
        "kanjiMeaning": "thừa trường",
        "meaning_vi": "bến xe / điểm lên xe",
        "meaning_en": "boarding place",
        "level": "N5",
        "tags": "minna_10,place"
    },
    {
        "term": "県",
        "reading": "けん",
        "kanjiMeaning": "huyện",
        "meaning_vi": "tỉnh / huyện",
        "meaning_en": "prefecture",
        "level": "N5",
        "tags": "minna_10,place"
    },
    {
        "term": "上",
        "reading": "うえ",
        "kanjiMeaning": "thượng",
        "meaning_vi": "trên",
        "meaning_en": "up / above",
        "level": "N5",
        "tags": "minna_10,position"
    },
    {
        "term": "下",
        "reading": "した",
        "kanjiMeaning": "hạ",
        "meaning_vi": "dưới",
        "meaning_en": "down / below",
        "level": "N5",
        "tags": "minna_10,position"
    },
    {
        "term": "前",
        "reading": "まえ",
        "kanjiMeaning": "tiền",
        "meaning_vi": "trước",
        "meaning_en": "front",
        "level": "N5",
        "tags": "minna_10,position"
    },
    {
        "term": "うしろ",
        "reading": "うしろ",
        "kanjiMeaning": null,
        "meaning_vi": "sau",
        "meaning_en": "back / behind",
        "level": "N5",
        "tags": "minna_10,position"
    },
    {
        "term": "右",
        "reading": "みぎ",
        "kanjiMeaning": "hữu",
        "meaning_vi": "phải",
        "meaning_en": "right",
        "level": "N5",
        "tags": "minna_10,position"
    },
    {
        "term": "左",
        "reading": "ひだり",
        "kanjiMeaning": "tả",
        "meaning_vi": "trái",
        "meaning_en": "left",
        "level": "N5",
        "tags": "minna_10,position"
    },
    {
        "term": "中",
        "reading": "なか",
        "kanjiMeaning": "trung",
        "meaning_vi": "trong",
        "meaning_en": "inside",
        "level": "N5",
        "tags": "minna_10,position"
    },
    {
        "term": "外",
        "reading": "そと",
        "kanjiMeaning": "ngoại",
        "meaning_vi": "ngoài",
        "meaning_en": "outside",
        "level": "N5",
        "tags": "minna_10,position"
    },
    {
        "term": "隣",
        "reading": "となり",
        "kanjiMeaning": "lân",
        "meaning_vi": "bên cạnh (cùng loại)",
        "meaning_en": "next to",
        "level": "N5",
        "tags": "minna_10,position"
    },
    {
        "term": "近く",
        "reading": "ちかく",
        "kanjiMeaning": "cận",
        "meaning_vi": "gần",
        "meaning_en": "near / neighborhood",
        "level": "N5",
        "tags": "minna_10,position"
    },
    {
        "term": "間",
        "reading": "あいだ",
        "kanjiMeaning": "gian",
        "meaning_vi": "giữa",
        "meaning_en": "between",
        "level": "N5",
        "tags": "minna_10,position"
    },
    {
        "term": "～や～など",
        "reading": "やなど",
        "kanjiMeaning": null,
        "meaning_vi": "~ và ~ (vân vân)",
        "meaning_en": "~ and ~, etc.",
        "level": "N5",
        "tags": "minna_10,particle"
    },
    {
        "term": "いちばん～",
        "reading": "いちばん",
        "kanjiMeaning": null,
        "meaning_vi": "~ nhất",
        "meaning_en": "the most ~",
        "level": "N5",
        "tags": "minna_10,adverb"
    },
    {
        "term": "チリソース",
        "reading": "ちりそーす",
        "kanjiMeaning": null,
        "meaning_vi": "tương ớt",
        "meaning_en": "Chili sauce",
        "level": "N5",
        "tags": "minna_10,food"
    }
]