[
  {
    "vocabId": "n4_l50_v001",
    "term": "参ります",
    "reading": "まいります",
    "kanjiMeaning": "tham",
    "level": "N4"
  },
  {
    "vocabId": "n4_l50_v002",
    "term": "おります",
    "reading": "おります",
    "kanjiMeaning": null,
    "level": "N4"
  },
  {
    "vocabId": "n4_l50_v003",
    "term": "いただきます",
    "reading": "いただきます",
    "kanjiMeaning": null,
    "level": "N4"
  },
  {
    "vocabId": "n4_l50_v004",
    "term": "申します",
    "reading": "もうします",
    "kanjiMeaning": "thân",
    "level": "N4"
  },
  {
    "vocabId": "n4_l50_v005",
    "term": "いたします",
    "reading": "いたします",
    "kanjiMeaning": null,
    "level": "N4"
  },
  {
    "vocabId": "n4_l50_v006",
    "term": "拝見します",
    "reading": "はいけんします",
    "kanjiMeaning": "bái kiến",
    "level": "N4"
  },
  {
    "vocabId": "n4_l50_v007",
    "term": "存じます",
    "reading": "ぞんじます",
    "kanjiMeaning": "tồn",
    "level": "N4"
  },
  {
    "vocabId": "n4_l50_v008",
    "term": "伺います",
    "reading": "うかがいます",
    "kanjiMeaning": "tứ",
    "level": "N4"
  },
  {
    "vocabId": "n4_l50_v009",
    "term": "お目に掛かります",
    "reading": "おめにかかります",
    "kanjiMeaning": "mục quải",
    "level": "N4"
  },
  {
    "vocabId": "n4_l50_v010",
    "term": "ございます",
    "reading": "ございます",
    "kanjiMeaning": null,
    "level": "N4"
  },
  {
    "vocabId": "n4_l50_v011",
    "term": "～でございます",
    "reading": "でございます",
    "kanjiMeaning": null,
    "level": "N4"
  },
  {
    "vocabId": "n4_l50_v012",
    "term": "私",
    "reading": "わたくし",
    "kanjiMeaning": "tư",
    "level": "N4"
  },
  {
    "vocabId": "n4_l50_v013",
    "term": "ガイド",
    "reading": "がいど",
    "kanjiMeaning": null,
    "level": "N4"
  },
  {
    "vocabId": "n4_l50_v014",
    "term": "お宅",
    "reading": "おたく",
    "kanjiMeaning": "trạch",
    "level": "N4"
  },
  {
    "vocabId": "n4_l50_v015",
    "term": "郊外",
    "reading": "こうがい",
    "kanjiMeaning": "giao ngoại",
    "level": "N4"
  },
  {
    "vocabId": "n4_l50_v016",
    "term": "アルバム",
    "reading": "あるばむ",
    "kanjiMeaning": null,
    "level": "N4"
  },
  {
    "vocabId": "n4_l50_v017",
    "term": "再来週",
    "reading": "さらいしゅう",
    "kanjiMeaning": "tái lai chu",
    "level": "N4"
  },
  {
    "vocabId": "n4_l50_v018",
    "term": "再来月",
    "reading": "さらいげつ",
    "kanjiMeaning": "tái lai nguyệt",
    "level": "N4"
  },
  {
    "vocabId": "n4_l50_v019",
    "term": "再来年",
    "reading": "さらいねん",
    "kanjiMeaning": "tái lai nên",
    "level": "N4"
  },
  {
    "vocabId": "n4_l50_v020",
    "term": "半年",
    "reading": "はんとし",
    "kanjiMeaning": "bán nên",
    "level": "N4"
  },
  {
    "vocabId": "n4_l50_v021",
    "term": "最初に",
    "reading": "さいしょに",
    "kanjiMeaning": "tối sơ",
    "level": "N4"
  },
  {
    "vocabId": "n4_l50_v022",
    "term": "最後に",
    "reading": "さいごに",
    "kanjiMeaning": "tối hậu",
    "level": "N4"
  },
  {
    "vocabId": "n4_l50_v023",
    "term": "ただ今",
    "reading": "ただいま",
    "kanjiMeaning": "kim",
    "level": "N4"
  },
  {
    "vocabId": "n4_l50_v024",
    "term": "緊張します",
    "reading": "きんちょうします",
    "kanjiMeaning": "khẩn trương",
    "level": "N4"
  },
  {
    "vocabId": "n4_l50_v025",
    "term": "放送します",
    "reading": "ほうそうします",
    "kanjiMeaning": "phóng tống",
    "level": "N4"
  },
  {
    "vocabId": "n4_l50_v026",
    "term": "ビデオに撮ります",
    "reading": "びでおにとります",
    "kanjiMeaning": "toát",
    "level": "N4"
  },
  {
    "vocabId": "n4_l50_v027",
    "term": "賞金",
    "reading": "しょうきん",
    "kanjiMeaning": "thưởng kim",
    "level": "N4"
  },
  {
    "vocabId": "n4_l50_v028",
    "term": "麒麟",
    "reading": "きりん",
    "kanjiMeaning": "kì lân",
    "level": "N4"
  },
  {
    "vocabId": "n4_l50_v029",
    "term": "象",
    "reading": "ぞう",
    "kanjiMeaning": "tượng",
    "level": "N4"
  },
  {
    "vocabId": "n4_l50_v030",
    "term": "ころ",
    "reading": "ころ",
    "kanjiMeaning": null,
    "level": "N4"
  },
  {
    "vocabId": "n4_l50_v031",
    "term": "かなえます",
    "reading": "かなえます",
    "kanjiMeaning": null,
    "level": "N4"
  },
  {
    "vocabId": "n4_l50_v032",
    "term": "一言よろしいでしょうか",
    "reading": "ひとことよろしいでしょうか",
    "kanjiMeaning": "nhất ngôn",
    "level": "N4"
  },
  {
    "vocabId": "n4_l50_v033",
    "term": "協力します",
    "reading": "きょうりょくします",
    "kanjiMeaning": "hiếp lực",
    "level": "N4"
  },
  {
    "vocabId": "n4_l50_v034",
    "term": "心から",
    "reading": "こころから",
    "kanjiMeaning": "tâm",
    "level": "N4"
  },
  {
    "vocabId": "n4_l50_v035",
    "term": "感謝します",
    "reading": "かんしゃします",
    "kanjiMeaning": "cảm tạ",
    "level": "N4"
  },
  {
    "vocabId": "n4_l50_v036",
    "term": "お礼",
    "reading": "おれい",
    "kanjiMeaning": "lễ",
    "level": "N4"
  },
  {
    "vocabId": "n4_l50_v037",
    "term": "拝啓",
    "reading": "はいけい",
    "kanjiMeaning": "bái khải",
    "level": "N4"
  },
  {
    "vocabId": "n4_l50_v038",
    "term": "美しい",
    "reading": "うつくしい",
    "kanjiMeaning": "mỉ",
    "level": "N4"
  },
  {
    "vocabId": "n4_l50_v039",
    "term": "お元気でいらっしゃいますか",
    "reading": "おげんきでいらっしゃいますか",
    "kanjiMeaning": "nguyên khí",
    "level": "N4"
  },
  {
    "vocabId": "n4_l50_v040",
    "term": "迷惑をかけます",
    "reading": "めいわくをかけます",
    "kanjiMeaning": "mê hoặc",
    "level": "N4"
  },
  {
    "vocabId": "n4_l50_v041",
    "term": "生かします",
    "reading": "いかします",
    "kanjiMeaning": "sinh",
    "level": "N4"
  },
  {
    "vocabId": "n4_l50_v042",
    "term": "敬具",
    "reading": "けいぐ",
    "kanjiMeaning": "kính cụ",
    "level": "N4"
  },
  {
    "vocabId": "n4_l50_v043",
    "term": "ミュンヘン",
    "reading": "みゅんへん",
    "kanjiMeaning": null,
    "level": "N4"
  },
  {
    "vocabId": "n4_l50_v044",
    "term": "お目にかかります",
    "reading": "おめにかかります",
    "kanjiMeaning": "mục",
    "level": "N4"
  },
  {
    "vocabId": "n4_l50_v045",
    "term": "自然",
    "reading": "しぜん",
    "kanjiMeaning": "tự nhiên",
    "level": "N4"
  },
  {
    "vocabId": "n4_l50_v046",
    "term": "撮ります",
    "reading": "とります",
    "kanjiMeaning": "toát",
    "level": "N4"
  },
  {
    "vocabId": "n4_l50_v047",
    "term": "江戸東京博物館",
    "reading": "えどとうきょうはくぶつかん",
    "kanjiMeaning": "giang hộ hốc kinh bác vật quán",
    "level": "N4"
  },
  {
    "vocabId": "n4_l50_v048",
    "term": "参加します",
    "reading": "さんかします",
    "kanjiMeaning": "tham gia",
    "level": "N4"
  },
  {
    "vocabId": "n4_l50_v049",
    "term": "参",
    "reading": "まい",
    "kanjiMeaning": "tham",
    "level": "N4"
  }
]
